android_sdk_platform_tools_supporter/__init__.py
android_sdk_platform_tools_supporter/android_sdk_platform_tools.py
android_sdk_platform_tools_supporter-0.0.5.dist-info/METADATA
android_sdk_platform_tools_supporter-0.0.5.dist-info/WHEEL
android_sdk_platform_tools_supporter-0.0.5.dist-info/top_level.txt
android_sdk_platform_tools_supporter-0.0.5.dist-info/RECORD
