Metadata-Version: 2.1
Name: android-sdk-platform-tools-supporter
Version: 0.0.5
Summary: Android sdk platform tools supporter
Home-page: https://github.com/automatethem/android-sdk-platform-tools-supporter
Author: Sang Ki Kwon
Author-email: automatethem@gmail.com
License: MIT
